[
    [
        {
            "current": "I was praying to small golden Buddha",
            "before": "",
            "beforewhen": null,
            "after": "",
            "afterwhen": null
        },
        {
            "current": " in a tunnel.",
            "before": "",
            "beforewhen": null,
            "after": "",
            "afterwhen": null
        },
        {
            "current": ". There were plants and offerings around the Buddha.",
            "before": "",
            "beforewhen": null,
            "after": "",
            "afterwhen": null
        },
        {
            "current": ". It was inside of a tourist park with a large ornamental tower.",
            "before": "",
            "beforewhen": null,
            "after": "",
            "afterwhen": null
        },
        {
            "current": ". It was in September 2019",
            "before": "",
            "beforewhen": null,
            "after": "",
            "afterwhen": null
        },
        {
            "current": " in Thailand.",
            "before": "",
            "beforewhen": null,
            "after": "",
            "afterwhen": null
        }
    ],
    [
        {
            "current": "I think it was the second time I visited the house with the stone shed / hovel.",
            "before": "",
            "beforewhen": null,
            "after": "",
            "afterwhen": null
        },
        {
            "current": ".  The shed was under green trees",
            "before": "",
            "beforewhen": null,
            "after": "",
            "afterwhen": null
        },
        {
            "current": " on a beautiful sunny day.",
            "before": "",
            "beforewhen": null,
            "after": "",
            "afterwhen": null
        },
        {
            "current": "",
            "before": "Drive",
            "beforewhen": "2",
            "after": "Drive Home",
            "afterwhen": "2"
        },
        {
            "current": ". It was in the middle of Ireland",
            "before": "Drive",
            "beforewhen": "2",
            "after": "Drive Home",
            "afterwhen": "2"
        },
        {
            "current": " on the 29th April 2020.",
            "before": "Drive",
            "beforewhen": "2",
            "after": "Drive Home",
            "afterwhen": "2"
        }
    ],
    [
        {
            "current": "In disaster prepper-mode, I was buying an oversized tin of beans",
            "before": "",
            "beforewhen": null,
            "after": "",
            "afterwhen": null
        },
        {
            "current": ", incase of emergencies when covid was starting.",
            "before": "",
            "beforewhen": null,
            "after": "",
            "afterwhen": null
        },
        {
            "current": ". I had looked at many large food items",
            "before": "",
            "beforewhen": null,
            "after": "",
            "afterwhen": null
        },
        {
            "current": " in a warehouse store called Musgrave MarketPlace",
            "before": "",
            "beforewhen": null,
            "after": "",
            "afterwhen": null
        },
        {
            "current": ", including honey and breakfast cereal and tuna fish.",
            "before": "",
            "beforewhen": null,
            "after": "",
            "afterwhen": null
        },
        {
            "current": ". It was in February 2020.",
            "before": "",
            "beforewhen": null,
            "after": "",
            "afterwhen": null
        }
    ],
    [
        {
            "current": "Mother Mary, pray for us!",
            "before": "",
            "beforewhen": null,
            "after": "",
            "afterwhen": null
        },
        {
            "current": " A religious image in front of a window",
            "before": "",
            "beforewhen": null,
            "after": "",
            "afterwhen": null
        },
        {
            "current": " on a Saturday morning",
            "before": "",
            "beforewhen": null,
            "after": "",
            "afterwhen": null
        },
        {
            "current": " in Dublin City University",
            "before": "",
            "beforewhen": null,
            "after": "",
            "afterwhen": null
        },
        {
            "current": "",
            "before": "coffee in a cafe",
            "beforewhen": null,
            "after": "coffee in a cafe",
            "afterwhen": null
        },
        {
            "current": ". August 31st",
            "before": "coffee in a cafe",
            "beforewhen": null,
            "after": "coffee in a cafe",
            "afterwhen": null
        }
    ],
    [
        {
            "current": "After a short relaxing walk, I reached the edge of a lake.",
            "before": "",
            "beforewhen": null,
            "after": "",
            "afterwhen": null
        },
        {
            "current": ". There were mountains",
            "before": "",
            "beforewhen": null,
            "after": "",
            "afterwhen": null
        },
        {
            "current": " and trees, but very few people.",
            "before": "",
            "beforewhen": null,
            "after": "",
            "afterwhen": null
        },
        {
            "current": ". It was a cold day",
            "before": "",
            "beforewhen": null,
            "after": "",
            "afterwhen": null
        },
        {
            "current": " in Spring",
            "before": "",
            "beforewhen": null,
            "after": "",
            "afterwhen": null
        },
        {
            "current": " in Wicklow in 2019.",
            "before": "",
            "beforewhen": null,
            "after": "",
            "afterwhen": null
        }
    ],
    [
        {
            "current": "Lots of colourful mugs for sale",
            "before": "",
            "beforewhen": null,
            "after": "",
            "afterwhen": null
        },
        {
            "current": " in Bangkok.",
            "before": "",
            "beforewhen": null,
            "after": "",
            "afterwhen": null
        },
        {
            "current": ". Yellow, red, green, blue, orange cups.",
            "before": "",
            "beforewhen": null,
            "after": "",
            "afterwhen": null
        },
        {
            "current": ". They were on a stand beside some green plants",
            "before": "",
            "beforewhen": null,
            "after": "",
            "afterwhen": null
        },
        {
            "current": " in a large outdoor mall.",
            "before": "",
            "beforewhen": null,
            "after": "",
            "afterwhen": null
        },
        {
            "current": "",
            "before": "",
            "beforewhen": null,
            "after": "eating dinner",
            "afterwhen": null
        }
    ],
    [
        {
            "current": "Greek wine on a Sunday.",
            "before": "",
            "beforewhen": null,
            "after": "",
            "afterwhen": null
        },
        {
            "current": ". I was in a Greek restaurant drinking a small bottle of wine",
            "before": "",
            "beforewhen": null,
            "after": "",
            "afterwhen": null
        },
        {
            "current": " and eating Greek food (chips and meat) with a salad.",
            "before": "",
            "beforewhen": null,
            "after": "",
            "afterwhen": null
        },
        {
            "current": ". I was sitting at a white tiled table.",
            "before": "",
            "beforewhen": null,
            "after": "",
            "afterwhen": null
        },
        {
            "current": ". It was in Thessaloniki in Greece",
            "before": "",
            "beforewhen": null,
            "after": "",
            "afterwhen": null
        },
        {
            "current": " in January 2019.",
            "before": "",
            "beforewhen": null,
            "after": "",
            "afterwhen": null
        }
    ],
    [
        {
            "current": "Cottage and shed for sale.",
            "before": "",
            "beforewhen": null,
            "after": "",
            "afterwhen": null
        },
        {
            "current": ". A stone cottage with a broken roof on the left side.",
            "before": "",
            "beforewhen": null,
            "after": "",
            "afterwhen": null
        },
        {
            "current": ". The cottage was surrounded by tall trees",
            "before": "",
            "beforewhen": null,
            "after": "",
            "afterwhen": null
        },
        {
            "current": " and had 4 windows and a door",
            "before": "",
            "beforewhen": null,
            "after": "",
            "afterwhen": null
        },
        {
            "current": " with yellow surrounds.",
            "before": "",
            "beforewhen": null,
            "after": "",
            "afterwhen": null
        },
        {
            "current": "",
            "before": "",
            "beforewhen": null,
            "after": "driving",
            "afterwhen": "0.2"
        }
    ],
    [
        {
            "current": "I remember there were two vinyl LPs (records)",
            "before": "",
            "beforewhen": null,
            "after": "",
            "afterwhen": null
        },
        {
            "current": " side by side on a  table.",
            "before": "",
            "beforewhen": null,
            "after": "",
            "afterwhen": null
        },
        {
            "current": ". One LP was from The Ventures and was called Knock Me Out.",
            "before": "",
            "beforewhen": null,
            "after": "",
            "afterwhen": null
        },
        {
            "current": ". The other featured the words Born Free and was an Invitation To The Movies by Matt Monro.",
            "before": "",
            "beforewhen": null,
            "after": "",
            "afterwhen": null
        },
        {
            "current": ". I was in Chiang Mai in Thailand.",
            "before": "",
            "beforewhen": null,
            "after": "",
            "afterwhen": null
        },
        {
            "current": " in January 2020.",
            "before": "",
            "beforewhen": null,
            "after": "",
            "afterwhen": null
        }
    ],
    [
        {
            "current": "Meeting friends outside a bar called the Brazen Head",
            "before": "",
            "beforewhen": null,
            "after": "",
            "afterwhen": null
        },
        {
            "current": "",
            "before": "",
            "beforewhen": null,
            "after": "walking to another bar for drinks.",
            "afterwhen": null
        },
        {
            "current": ". It was in September",
            "before": "",
            "beforewhen": null,
            "after": "",
            "afterwhen": null
        },
        {
            "current": "in 2019",
            "before": "",
            "beforewhen": null,
            "after": "",
            "afterwhen": null
        },
        {
            "current": ", on a Friday evening.",
            "before": "",
            "beforewhen": null,
            "after": "",
            "afterwhen": null
        },
        {
            "current": "",
            "before": "getting a taxi",
            "beforewhen": null,
            "after": "",
            "afterwhen": null
        }
    ],
    [
        {
            "current": "\"Get back\" on the roof.",
            "before": "",
            "beforewhen": null,
            "after": "",
            "afterwhen": null
        },
        {
            "current": ". I was watching the Beatles rooftop concert on tv (not in music metadata).",
            "before": "",
            "beforewhen": null,
            "after": "",
            "afterwhen": null
        },
        {
            "current": ". I was at home watching youtube on TV for about 90 minutes",
            "before": "",
            "beforewhen": null,
            "after": "",
            "afterwhen": null
        },
        {
            "current": "",
            "before": "doing some computer work.",
            "beforewhen": null,
            "after": "",
            "afterwhen": null
        },
        {
            "current": ". It was in April",
            "before": "doing some computer work.",
            "beforewhen": null,
            "after": "",
            "afterwhen": null
        },
        {
            "current": " 2019.",
            "before": "doing some computer work.",
            "beforewhen": null,
            "after": "",
            "afterwhen": null
        }
    ],
    [
        {
            "current": "Zombies on the platform?",
            "before": "",
            "beforewhen": null,
            "after": "",
            "afterwhen": null
        },
        {
            "current": " I was waiting for a train in a station was featured in the movie \"Last Train To Busan\".",
            "before": "",
            "beforewhen": null,
            "after": "",
            "afterwhen": null
        },
        {
            "current": ". But there were no zombies, just my friends",
            "before": "",
            "beforewhen": null,
            "after": "",
            "afterwhen": null
        },
        {
            "current": ", one of whom was wearing a blue jacket.",
            "before": "",
            "beforewhen": null,
            "after": "",
            "afterwhen": null
        },
        {
            "current": "",
            "before": "taken a taxi to Daejeon station",
            "beforewhen": null,
            "after": "",
            "afterwhen": null
        },
        {
            "current": " January 2020.",
            "before": "taken a taxi to Daejeon station",
            "beforewhen": null,
            "after": "",
            "afterwhen": null
        }
    ],
    [
        {
            "current": "Preaching to a full room.",
            "before": "",
            "beforewhen": null,
            "after": "",
            "afterwhen": null
        },
        {
            "current": ". My hands were out in front of me",
            "before": "",
            "beforewhen": null,
            "after": "",
            "afterwhen": null
        },
        {
            "current": ", I was speaking to a room of about 200 people",
            "before": "",
            "beforewhen": null,
            "after": "",
            "afterwhen": null
        },
        {
            "current": " seated at dinner tables.",
            "before": "",
            "beforewhen": null,
            "after": "",
            "afterwhen": null
        },
        {
            "current": ". It was in Korea",
            "before": "",
            "beforewhen": null,
            "after": "",
            "afterwhen": null
        },
        {
            "current": " in January 2020 at the MMM conference.",
            "before": "",
            "beforewhen": null,
            "after": "",
            "afterwhen": null
        }
    ],
    [
        {
            "current": "Buying hand soaps in a shop called Molton Brown",
            "before": "",
            "beforewhen": null,
            "after": "",
            "afterwhen": null
        },
        {
            "current": " in the early morning.",
            "before": "",
            "beforewhen": null,
            "after": "",
            "afterwhen": null
        },
        {
            "current": ". I was at an outside shopping mall",
            "before": "",
            "beforewhen": null,
            "after": "",
            "afterwhen": null
        },
        {
            "current": "",
            "before": "driving a long way",
            "beforewhen": null,
            "after": "",
            "afterwhen": null
        },
        {
            "current": " that morning",
            "before": "driving a long way",
            "beforewhen": null,
            "after": "",
            "afterwhen": null
        },
        {
            "current": " in June 2020.",
            "before": "driving a long way",
            "beforewhen": null,
            "after": "",
            "afterwhen": null
        }
    ]
]